PyL360/__init__.py
PyL360/dto_models.py
pyl360-0.1.10.dist-info/METADATA
pyl360-0.1.10.dist-info/WHEEL
pyl360-0.1.10.dist-info/top_level.txt
pyl360-0.1.10.dist-info/RECORD
