Metadata-Version: 2.4
Name: PyL360
Version: 0.1.10
Summary: A package for interfacing with Life360
Home-page: https://github.com/arkangel-dev/PyL360
Author: Sam Ramirez
Classifier: Programming Language :: Python :: 3
Requires-Python: >=3.6
Requires-Dist: certifi==2024.12.14
Requires-Dist: charset-normalizer==3.4.1
Requires-Dist: dacite==1.8.1
Requires-Dist: idna==3.10
Requires-Dist: requests==2.32.3
Requires-Dist: tls-client==1.0.1
Requires-Dist: typing_extensions==4.12.2
Requires-Dist: urllib3==2.3.0
Dynamic: author
Dynamic: classifier
Dynamic: description
Dynamic: description-content-type
Dynamic: home-page
Dynamic: requires-dist
Dynamic: requires-python
Dynamic: summary
